cloudflare_workers/__init__.py
cloudflare_workers/key_value_store.py
cloudflare_workers-0.0.1.dist-info/LICENSE
cloudflare_workers-0.0.1.dist-info/METADATA
cloudflare_workers-0.0.1.dist-info/WHEEL
cloudflare_workers-0.0.1.dist-info/top_level.txt
cloudflare_workers-0.0.1.dist-info/RECORD
